Workbook

Sheet Inputs
A1: Heathrow Logistics Hub — Acquisition Assumptions
A3: I. Asset Profile & Timeline
A4: Gross Lettable Area (GLA) | B4: 150000 | C4: sq. ft.
A5: Acquisition Close Date | B5: 46388
A6: Hold Period | B6: 5 | C6: Years
A8: II. Acquisition Capitalization
A9: Purchase Price | B9: 25000000 | C9: Base purchase price
A10: Acquisition Costs (%) | B10: 0.045 | C10: SDLT & legal fees
A11: Acquisition Costs (£) | B11: =B9*B10 -> 1125000 | C11: SDLT & transaction costs
A12: Total Acquisition Basis (Uses) | B12: =B9+B11 -> 26125000 | C12: Total gross capital required
A14: III. Operations & Underwriting
A15: Base In-Place Rent (Year 1) | B15: 12.5 | C15: per sq. ft. / yr
A16: Annual Rent Escalation | B16: 0.035 | C16: Annual contractual
A17: General Vacancy & Credit Loss | B17: 0.03 | C17: % of PGI
A18: Operating Expenses (OpEx % of EGI) | B18: 0.05 | C18: FRI Lease baseline
A19: CapEx Reserve per sq. ft. | B19: 0.25 | C19: per sq. ft.
A20: Year 4 Tenant Refurb / Renewal Reserve | B20: 150000 | C20: Tenant renewal allowance
A22: IV. Debt Financing (Senior Facility)
A23: Loan-to-Value (LTV) | B23: 0.65 | C23: Senior debt %
A24: Senior Loan Commitment | B24: 16250000 | C24: Senior loan facility
A25: Interest Rate (Fixed) | B25: 0.0525 | C25: Per annum
A26: Interest-Only (IO) Period | B26: 2 | C26: Years
A27: Amortization Term (Post-IO) | B27: 25 | C27: Years (300 months)
A28: Minimum Target DSCR Covenant | B28: 1.35x | C28: Minimum debt coverage
A30: V. DISPOSITION & TERMINAL VALUE
A31: Target Exit Cap Rate | B31: 0.05 | C31: Exit yield
A32: Sale & Disposition Costs | B32: 0.02 | C32: Broker / legal fee at exit
A34: VI. SOURCES & USES SUMMARY
A35: Senior Debt Facility | B35: 16250000 | C35: Senior debt
A36: Sponsor Equity Required | B36: 9875000 | C36: Equity required
A37: Total Sources Check | B37: =B35+B36 -> 26125000 | C37: Sources / Uses balance check

Sheet Pro_Forma
A3: Heathrow Logistics Hub — 5-Year Cash Flow Pro-Forma Waterfall
A5: Operating Line Item | B5: Year 1 | C5: Year 2 | D5: Year 3 | E5: Year 4 | F5: Year 5 | G5: Year 6(Exit Underwrite)
A6: Contractual Rent / sq. ft. | B6: =Inputs!B15 -> 12.5 | C6: =B6*(1+Inputs!$B$16) -> 12.9375 | D6: =C6*(1+Inputs!$B$16) -> 13.390312 | E6: =D6*(1+Inputs!$B$16) -> 13.858973 | F6: =E6*(1+Inputs!$B$16) -> 14.344038 | G6: =F6*(1+Inputs!$B$16) -> 14.846079
A7: Potential Gross Income (PGI) | B7: =Inputs!$B$4*B6 -> 1875000 | C7: =Inputs!$B$4*C6 -> 1940625 | D7: =Inputs!$B$4*D6 -> 2008546.9 | E7: =Inputs!$B$4*E6 -> 2078846 | F7: =Inputs!$B$4*F6 -> 2151605.6 | G7: =Inputs!$B$4*G6 -> 2226911.8
A8: Less: Vacancy & Credit Loss (3%) | B8: =-B7*Inputs!$B$17 -> -56250 | C8: =-C7*Inputs!$B$17 -> -58218.75 | D8: =-D7*Inputs!$B$17 -> -60256.406 | E8: =-E7*Inputs!$B$17 -> -62365.38 | F8: =-F7*Inputs!$B$17 -> -64548.169 | G8: =-G7*Inputs!$B$17 -> -66807.355
A9: Effective Gross Income (EGI) | B9: =B7+B8 -> 1818750 | C9: =C7+C8 -> 1882406.2 | D9: =D7+D8 -> 1948290.5 | E9: =E7+E8 -> 2016480.6 | F9: =F7+F8 -> 2087057.5 | G9: =G7+G8 -> 2160104.5
A10: Less: Operating Expenses (5% of EGI) | B10: =-B9*Inputs!$B$18 -> -90937.5 | C10: =-C9*Inputs!$B$18 -> -94120.312 | D10: =-D9*Inputs!$B$18 -> -97414.523 | E10: =-E9*Inputs!$B$18 -> -100824.03 | F10: =-F9*Inputs!$B$18 -> -104352.87 | G10: =-G9*Inputs!$B$18 -> -108005.22
A11: Less: CapEx Reserve (£0.25/sq. ft.) | B11: =-Inputs!$B$4*Inputs!$B$19 -> -37500 | C11: =-Inputs!$B$4*Inputs!$B$19 -> -37500 | D11: =-Inputs!$B$4*Inputs!$B$19 -> -37500 | E11: =-Inputs!$B$4*Inputs!$B$19 -> -37500 | F11: =-Inputs!$B$4*Inputs!$B$19 -> -37500 | G11: =-Inputs!$B$4*Inputs!$B$19 -> -37500
A12: Net Operating Income (NOI) | B12: =B9+B10+B11 -> 1690312.5 | C12: =C9+C10+C11 -> 1750785.9 | D12: =D9+D10+D11 -> 1813375.9 | E12: =E9+E10+E11 -> 1878156.6 | F12: =F9+F10+F11 -> 1945204.6 | G12: =G9+G10+G11 -> 2014599.2
A14: Less: Tenant Improvement & Refurb | B14: 0 | C14: 0 | D14: 0 | E14: =-Inputs!B20 -> -150000 | F14: 0 | G14: 0
A15: Cash Flow Before Debt (Unlevered CF) | B15: =B12+B14 -> 1690312.5 | C15: =C12+C14 -> 1750785.9 | D15: =D12+D14 -> 1813375.9 | E15: =E12+E14 -> 1728156.6 | F15: =F12+F14 -> 1945204.6 | G15: =G12+G14 -> 2014599.2
A17: Less: Total Debt Service | B17: =-Debt_Schedule!C10 -> -853125 | C17: =-Debt_Schedule!D10 -> -853125 | D17: =-Debt_Schedule!E10 -> -1182035.7 | E17: =-Debt_Schedule!F10 -> -1182035.7 | F17: =-Debt_Schedule!G10 -> -1182035.7
A18: Cash Flow After Debt (Levered CF) | B18: =B15+B17 -> 837187.5 | C18: =C15+C17 -> 897660.94 | D18: =D15+D17 -> 631340.27 | E18: =E15+E17 -> 546120.93 | F18: =F15+F17 -> 763168.91
A20: Debt Service Coverage Ratio (DSCR) | B20: =B12/Debt_Schedule!C10 -> 1.9813187 | C20: =C12/Debt_Schedule!D10 -> 2.0522033 | D20: =D12/Debt_Schedule!E10 -> 1.5341127 | E20: =E12/Debt_Schedule!F10 -> 1.588917 | F20: =F12/Debt_Schedule!G10 -> 1.6456395
A21: DSCR Covenant Compliance (Min 1.35x) | B21: =IF(B20>=1.35,"PASS","FAIL") -> PASS | C21: =IF(C20>=1.35,"PASS","FAIL") -> PASS | D21: =IF(D20>=1.35,"PASS","FAIL") -> PASS | E21: =IF(E20>=1.35,"PASS","FAIL") -> PASS | F21: =IF(F20>=1.35,"PASS","FAIL") -> PASS

Sheet Debt_Schedule
A3: Heathrow Logistics Hub — Senior Debt Financing Schedule
A5: Period / Line Item | B5: Year 0 (Close) | C5: Year 1 | D5: Year 2 | E5: Year 3 | F5: Year 4 | G5: Year 5
A6: Beginning Balance | C6: =Inputs!B24 -> 16250000 | D6: =C11 -> 16250000 | E6: =D11 -> 16250000 | F6: =E11 -> 15921089 | G6: =F11 -> 15574911
A7: Senior Debt Facility Drawdown | B7: =Inputs!B24 -> 16250000
A8: Interest Expense (5.25%) | C8: =C6*Inputs!$B$25 -> 853125 | D8: =D6*Inputs!$B$25 -> 853125 | E8: =E6*Inputs!$B$25 -> 853125 | F8: =F6*Inputs!$B$25 -> 835857.19 | G8: =G6*Inputs!$B$25 -> 817682.82
A9: Principal Repayment / Amortization | C9: 0 | D9: 0 | E9: =PMT(Inputs!$B$25, Inputs!$B$27, -Inputs!$B$24) - E8 -> 328910.68 | F9: =PMT(Inputs!$B$25, Inputs!$B$27, -Inputs!$B$24) - F8 -> 346178.49 | G9: =PMT(Inputs!$B$25, Inputs!$B$27, -Inputs!$B$24) - G8 -> 364352.86
A10: Total Debt Service | C10: =C8+C9 -> 853125 | D10: =D8+D9 -> 853125 | E10: =E8+E9 -> 1182035.7 | F10: =F8+F9 -> 1182035.7 | G10: =G8+G9 -> 1182035.7
A11: Ending Principal Balance | B11: =B7 -> 16250000 | C11: =C6-C9 -> 16250000 | D11: =D6-D9 -> 16250000 | E11: =E6-E9 -> 15921089 | F11: =F6-F9 -> 15574911 | G11: =G6-G9 -> 15210558

Sheet Returns_Sensitivity
A3: Heathrow Logistics Hub — Investment Returns & Disposition Waterfall
A5: I. Disposition & Terminal Valuation
A6: Forward Year 6 NOI | B6: =Pro_Forma!G12 -> 2014599.2
A7: Terminal Exit Cap Rate | B7: =D31 -> 0.05
A8: Gross Disposition Price | B8: =B6/B7 -> 40291985
A9: Less: Disposition & Broker Costs (2%) | B9: =-B8*Inputs!B32 -> -805839.7
A10: Net Disposition Value | B10: =B8+B9 -> 39486145
A11: Less: Senior Debt Payoff (Year 5 Ending Balance) | B11: =-Debt_Schedule!G11 -> -15210558
A12: Net Disposition Proceeds to Equity | B12: =B10+B11 -> 24275587
A14: II. Unlevered Returns (Asset-Level)
A15: Initial Acquisition Basis
A16: Unlevered IRR | B16: =IRR(B26:G26) -> 0.14453644
A17: Unlevered Equity Multiple | B17: =SUM(C26:G26)/(-B26) -> 1.8531667
A19: III. Levered Returns (Equity-Level)
A20: Initial Equity Invested
A21: Levered IRR | B21: =IRR(B27:G27) -> 0.25340684
A22: Levered Equity Multiple (MOIC) | B22: =SUM(C27:G27)/(-B27) -> 2.8304877
A25: Hold Period | B25: Year 0(Close) | C25: Year 1 | D25: Year 2 | E25: Year 3 | F25: Year 4 | G25: Year 5
A26: Total Unlevered Cash Flow | B26: =-(D30*(1+Inputs!$B$10)) -> -26125000 | C26: =Pro_Forma!B15 -> 1690312.5 | D26: =Pro_Forma!C15 -> 1750785.9 | E26: =Pro_Forma!D15 -> 1813375.9 | F26: =Pro_Forma!E15 -> 1728156.6 | G26: =Pro_Forma!F15+B10 -> 41431350
A27: Total Levered Equity Cash Flow | B27: =-((D30*(1+Inputs!$B$10)) - (D30*Inputs!$B$23)) -> -9875000 | C27: =Pro_Forma!B18 -> 837187.5 | D27: =Pro_Forma!C18 -> 897660.94 | E27: =Pro_Forma!D18 -> 631340.27 | F27: =Pro_Forma!E18 -> 546120.93 | G27: =Pro_Forma!F18+B12 -> 25038756
C30: Base Price: | D30: =Inputs!B9 -> 25000000
A31: IV. Levered IRR Sensitivity Matrix | C31: Base Cap Rate: | D31: =Inputs!B31 -> 0.05
B33: =B21 -> 0.25340684 | C33: 23000000 | D33: 24000000 | E33: 25000000 | F33: 26000000 | G33: 27000000
B34: 0.045 | C34: 0.31547019 | D34: 0.30301706 | E34: 0.29121875 | F34: 0.28001542 | G34: 0.26935481
B35: 0.0475 | C35: 0.29586653 | D35: 0.28356237 | E35: 0.27190633 | F35: 0.2608391 | G35: 0.25030889
B36: 0.05 | C36: 0.27708961 | D36: 0.26492734 | E36: 0.25340684 | F36: 0.24246929 | G36: 0.23206336
B37: 0.0525 | C37: 0.25903718 | D37: 0.24701053 | E37: 0.23561962 | F37: 0.22480608 | G37: 0.21451902
B38: 0.055 | C38: 0.24162097 | D38: 0.22972439 | E38: 0.21845777 | F38: 0.20776321 | G38: 0.19759021
B39: 0.06 | C39: 0.20839852 | D39: 0.19674771 | E39: 0.18571604 | F39: 0.17524646 | G39: 0.16528921
